{"__symbolic":"module","version":4,"exports":[{"export":[{"name":"UserModel","as":"UserModel"}],"from":"./lib/models"},{"export":[{"name":"SignInActionTypes","as":"SignInActionTypes"},{"name":"DoSignoutAction","as":"DoSignoutAction"},{"name":"AuthenticationActionTypes","as":"AuthenticationActionTypes"},{"name":"SigninRequiredAction","as":"SigninRequiredAction"}],"from":"./lib/actions"}],"metadata":{"SigninService":{"__symbolic":"class","decorators":[{"__symbolic":"call","expression":{"__symbolic":"reference","module":"@angular/core","name":"Injectable","line":15,"character":1},"arguments":[{"providedIn":"root"}]}],"members":{"__ctor__":[{"__symbolic":"constructor","parameters":[{"__symbolic":"reference","module":"@angular/common/http","name":"HttpClient","line":20,"character":16},{"__symbolic":"reference","name":"Store","module":"@ngrx/store","arguments":[{"__symbolic":"reference","name":"ɵe"}]},{"__symbolic":"reference","name":"ɵf"},{"__symbolic":"reference","module":"@angular/material","name":"MatSnackBar","line":23,"character":20}]}],"signup":[{"__symbolic":"method"}],"signin":[{"__symbolic":"method"}],"signout":[{"__symbolic":"method"}],"whoAmI":[{"__symbolic":"method"}]},"statics":{"ngInjectableDef":{}}},"SigninContainerComponent":{"__symbolic":"class","decorators":[{"__symbolic":"call","expression":{"__symbolic":"reference","module":"@angular/core","name":"Component","line":8,"character":1},"arguments":[{"template":"\n        <auth-signin \n                [formId]='(formId$ | async)'\n                (signedin)=\"signIn($event)\"\n        ></auth-signin>\n  "}]}],"members":{"signedIn$":[{"__symbolic":"property","decorators":[{"__symbolic":"call","expression":{"__symbolic":"reference","module":"@angular/core","name":"Output","line":18,"character":2}}]}],"__ctor__":[{"__symbolic":"constructor","parameters":[{"__symbolic":"reference","name":"ɵf"},{"__symbolic":"reference","name":"Store","module":"@ngrx/store","arguments":[{"__symbolic":"reference","name":"ɵe"}]}]}],"signIn":[{"__symbolic":"method"}]}},"ɵa":{"__symbolic":"class","decorators":[{"__symbolic":"call","expression":{"__symbolic":"reference","module":"@angular/core","name":"NgModule","line":109,"character":1},"arguments":[{"imports":[{"__symbolic":"call","expression":{"__symbolic":"select","expression":{"__symbolic":"reference","module":"@ngrx/store","name":"StoreModule","line":111,"character":2},"member":"forFeature"},"arguments":["authentication",{"__symbolic":"reference","name":"ɵb"}]},{"__symbolic":"call","expression":{"__symbolic":"select","expression":{"__symbolic":"reference","module":"@ngrx/effects","name":"EffectsModule","line":112,"character":2},"member":"forFeature"},"arguments":[[{"__symbolic":"reference","name":"ɵp"},{"__symbolic":"reference","name":"ɵq"}]]},{"__symbolic":"reference","name":"ɵr"},{"__symbolic":"reference","name":"NgsAuthenticationModule"}]}]}],"members":{}},"NgsAuthenticationModule":{"__symbolic":"class","decorators":[{"__symbolic":"call","expression":{"__symbolic":"reference","module":"@angular/core","name":"NgModule","line":48,"character":1},"arguments":[{"imports":[{"__symbolic":"reference","module":"@angular/common","name":"CommonModule","line":50,"character":2},{"__symbolic":"reference","module":"@angular/router","name":"RouterModule","line":51,"character":2},{"__symbolic":"reference","module":"@angular/forms","name":"FormsModule","line":52,"character":2},{"__symbolic":"reference","module":"@angular/common/http","name":"HttpClientModule","line":53,"character":2},{"__symbolic":"reference","module":"@angular/flex-layout","name":"FlexLayoutModule","line":54,"character":2},{"__symbolic":"reference","module":"@angular/material","name":"MatIconModule","line":55,"character":2},{"__symbolic":"reference","module":"@angular/material","name":"MatButtonModule","line":56,"character":2},{"__symbolic":"reference","module":"@angular/material","name":"MatCardModule","line":57,"character":2},{"__symbolic":"reference","module":"@angular/material","name":"MatSnackBarModule","line":58,"character":2},{"__symbolic":"reference","module":"@angular/material","name":"MatSidenavModule","line":59,"character":2},{"__symbolic":"reference","module":"@angular/material","name":"MatExpansionModule","line":60,"character":2},{"__symbolic":"reference","module":"@angular/material","name":"MatSelectModule","line":61,"character":2},{"__symbolic":"reference","module":"@angular/material","name":"MatBottomSheetModule","line":62,"character":2},{"__symbolic":"reference","module":"@angular/material","name":"MatFormFieldModule","line":63,"character":2},{"__symbolic":"reference","module":"@angular/material","name":"MatListModule","line":64,"character":2},{"__symbolic":"reference","module":"@angular/material","name":"MatMenuModule","line":65,"character":2},{"__symbolic":"reference","module":"@angular/material","name":"MatRadioModule","line":66,"character":2},{"__symbolic":"reference","module":"@angular/material","name":"MatInputModule","line":67,"character":2},{"__symbolic":"reference","module":"@angular/material","name":"MatToolbarModule","line":68,"character":2},{"__symbolic":"reference","module":"@angular/material","name":"MatDatepickerModule","line":69,"character":2},{"__symbolic":"reference","module":"@angular/material","name":"MatProgressBarModule","line":70,"character":2},{"__symbolic":"reference","module":"@angular/platform-browser/animations","name":"BrowserAnimationsModule","line":71,"character":2},{"__symbolic":"reference","module":"@angular/forms","name":"ReactiveFormsModule","line":72,"character":2},{"__symbolic":"reference","module":"@angular/forms","name":"FormsModule","line":73,"character":2},{"__symbolic":"reference","module":"@soushians/form","name":"NgsFormModule","line":74,"character":2}],"declarations":[{"__symbolic":"reference","name":"SigninContainerComponent"},{"__symbolic":"reference","name":"ɵi"},{"__symbolic":"reference","name":"ɵj"},{"__symbolic":"reference","name":"ɵk"},{"__symbolic":"reference","name":"ɵl"}],"entryComponents":[{"__symbolic":"reference","name":"SigninContainerComponent"}],"providers":[{"__symbolic":"reference","name":"ɵm"}],"exports":[]}]}],"members":{},"statics":{"forRoot":{"__symbolic":"function","parameters":["config"],"defaults":[{}],"value":{"ngModule":{"__symbolic":"reference","name":"ɵa"},"providers":[{"provide":{"__symbolic":"reference","name":"ɵg"},"useValue":{"__symbolic":"reference","name":"config"}},{"provide":{"__symbolic":"reference","module":"@angular/common/http","name":"HTTP_INTERCEPTORS","line":94,"character":14},"useClass":{"__symbolic":"reference","name":"ɵs"},"multi":true},{"provide":{"__symbolic":"reference","module":"@angular/common/http","name":"HTTP_INTERCEPTORS","line":99,"character":14},"useClass":{"__symbolic":"reference","name":"ɵt"},"multi":true},{"__symbolic":"reference","name":"SigninService"}]}}}},"ɵb":{"userStatus":{"__symbolic":"reference","name":"ɵn"}},"ɵc":{"__symbolic":"call","expression":{"__symbolic":"reference","module":"@ngrx/store","name":"createFeatureSelector","line":23,"character":41},"arguments":["authentication"]},"ɵd":{"__symbolic":"call","expression":{"__symbolic":"reference","module":"@ngrx/store","name":"createSelector","line":25,"character":31},"arguments":[{"__symbolic":"reference","name":"ɵc"},{"__symbolic":"error","message":"Lambda not supported","line":27,"character":1,"module":"./lib/reducers/index"}]},"getUser":{"__symbolic":"call","expression":{"__symbolic":"reference","module":"@ngrx/store","name":"createSelector","line":31,"character":23},"arguments":[{"__symbolic":"reference","name":"ɵd"},{"__symbolic":"reference","name":"ɵo"}]},"ɵf":{"__symbolic":"class","decorators":[{"__symbolic":"call","expression":{"__symbolic":"reference","module":"@angular/core","name":"Injectable","line":10,"character":1},"arguments":[{"providedIn":"root"}]}],"members":{"__ctor__":[{"__symbolic":"constructor","parameterDecorators":[[{"__symbolic":"call","expression":{"__symbolic":"reference","module":"@angular/core","name":"Inject","line":20,"character":14},"arguments":[{"__symbolic":"reference","name":"ɵg"}]}],null],"parameters":[{"__symbolic":"reference","name":"any"},{"__symbolic":"reference","name":"Store","module":"@ngrx/store","arguments":[{"__symbolic":"reference","name":"ɵh"}]}]}]},"statics":{"ngInjectableDef":{}}},"ɵg":{"__symbolic":"new","expression":{"__symbolic":"reference","module":"@angular/core","name":"InjectionToken","line":45,"character":39},"arguments":["ModuleConfig"]},"ɵi":{"__symbolic":"class","decorators":[{"__symbolic":"call","expression":{"__symbolic":"reference","module":"@angular/core","name":"Component","line":4,"character":1},"arguments":[{"selector":"auth-signin","template":"<div fxLayout='row' fxLayoutAlign=\"center center\">\n    <ngs-form-view \n        [id]=\"formId\"\n        [card]=\"true\"\n        (accept)=\"signin($event)\"\n    ></ngs-form-view>\n</div>\n<!-- <div>\n    <a fxFlex=\"nogrow\" routerLink=\"/user/password/reset\" mat-raised-button fxFlexFill>کلمه عبور خود را فراموش کرده اید؟</a>\n</div> -->","styles":[""]}]}],"members":{"signedin":[{"__symbolic":"property","decorators":[{"__symbolic":"call","expression":{"__symbolic":"reference","module":"@angular/core","name":"Output","line":19,"character":2}}]}],"formId":[{"__symbolic":"property","decorators":[{"__symbolic":"call","expression":{"__symbolic":"reference","module":"@angular/core","name":"Input","line":21,"character":2}}]}],"signin":[{"__symbolic":"method"}],"__ctor__":[{"__symbolic":"constructor"}]}},"ɵj":{"__symbolic":"class","decorators":[{"__symbolic":"call","expression":{"__symbolic":"reference","module":"@angular/core","name":"Component","line":2,"character":1},"arguments":[{"template":"\n          <router-outlet></router-outlet>\n        "}]}],"members":{}},"ɵk":{"__symbolic":"class","decorators":[{"__symbolic":"call","expression":{"__symbolic":"reference","module":"@angular/core","name":"Component","line":11,"character":1},"arguments":[{"template":"\n        <auth-signup \n                [formId]='(formId$ | async)'\n                (signedup)=\"signup($event)\"\n        ></auth-signup>\n  "}]}],"members":{"signedUp$":[{"__symbolic":"property","decorators":[{"__symbolic":"call","expression":{"__symbolic":"reference","module":"@angular/core","name":"Output","line":21,"character":2}}]}],"__ctor__":[{"__symbolic":"constructor","parameters":[{"__symbolic":"reference","name":"ɵf"},{"__symbolic":"reference","name":"Store","module":"@ngrx/store","arguments":[{"__symbolic":"reference","name":"ɵe"}]},{"__symbolic":"reference","module":"@angular/material","name":"MatSnackBar","line":25,"character":20}]}],"signup":[{"__symbolic":"method"}]}},"ɵl":{"__symbolic":"class","decorators":[{"__symbolic":"call","expression":{"__symbolic":"reference","module":"@angular/core","name":"Component","line":4,"character":1},"arguments":[{"selector":"auth-signup","template":"<div fxLayout='row' fxLayoutAlign=\"center center\">\n    <ngs-form-view \n        [id]=\"formId\"\n        [card]=\"true\"\n        (accept)=\"signup($event)\"\n    ></ngs-form-view>\n</div>\n<!-- <div>\n    <a fxFlex=\"nogrow\" routerLink=\"/user/password/reset\" mat-raised-button fxFlexFill>کلمه عبور خود را فراموش کرده اید؟</a>\n</div> -->","styles":[""]}]}],"members":{"signedup":[{"__symbolic":"property","decorators":[{"__symbolic":"call","expression":{"__symbolic":"reference","module":"@angular/core","name":"Output","line":19,"character":2}}]}],"formId":[{"__symbolic":"property","decorators":[{"__symbolic":"call","expression":{"__symbolic":"reference","module":"@angular/core","name":"Input","line":21,"character":2}}]}],"signup":[{"__symbolic":"method"}],"__ctor__":[{"__symbolic":"constructor"}]}},"ɵm":{"__symbolic":"class","decorators":[{"__symbolic":"call","expression":{"__symbolic":"reference","module":"@angular/core","name":"Injectable","line":7,"character":1}}],"members":{"__ctor__":[{"__symbolic":"constructor","parameters":[{"__symbolic":"reference","name":"Store","module":"@ngrx/store","arguments":[{"__symbolic":"reference","name":"ɵe"}]}]}],"canActivate":[{"__symbolic":"method"}]}},"ɵn":{"__symbolic":"function"},"ɵo":{"__symbolic":"error","message":"Lambda not supported","line":39,"character":23,"module":"./lib/reducers/user.reducer"},"ɵp":{"__symbolic":"class","decorators":[{"__symbolic":"call","expression":{"__symbolic":"reference","module":"@angular/core","name":"Injectable","line":25,"character":1}}],"members":{"__ctor__":[{"__symbolic":"constructor","parameters":[{"__symbolic":"reference","module":"@ngrx/effects","name":"Actions","line":28,"character":20},{"__symbolic":"reference","module":"@angular/router","name":"Router","line":29,"character":18},{"__symbolic":"reference","name":"SigninService"},{"__symbolic":"reference","name":"ɵf"},{"__symbolic":"reference","module":"@angular/material","name":"MatBottomSheet","line":32,"character":23}]}],"whoAmI$":[{"__symbolic":"property","decorators":[{"__symbolic":"call","expression":{"__symbolic":"reference","module":"@ngrx/effects","name":"Effect","line":35,"character":2}}]}],"Signin$":[{"__symbolic":"property","decorators":[{"__symbolic":"call","expression":{"__symbolic":"reference","module":"@ngrx/effects","name":"Effect","line":46,"character":2}}]}],"signup$":[{"__symbolic":"property","decorators":[{"__symbolic":"call","expression":{"__symbolic":"reference","module":"@ngrx/effects","name":"Effect","line":58,"character":2}}]}],"signupSucceed$":[{"__symbolic":"property","decorators":[{"__symbolic":"call","expression":{"__symbolic":"reference","module":"@ngrx/effects","name":"Effect","line":70,"character":2},"arguments":[{"dispatch":false}]}]}],"SignInRequired$":[{"__symbolic":"property","decorators":[{"__symbolic":"call","expression":{"__symbolic":"reference","module":"@ngrx/effects","name":"Effect","line":78,"character":2},"arguments":[{"dispatch":false}]}]}],"SigninSucceed$":[{"__symbolic":"property","decorators":[{"__symbolic":"call","expression":{"__symbolic":"reference","module":"@ngrx/effects","name":"Effect","line":91,"character":2},"arguments":[{"dispatch":false}]}]}],"AfterSigninFiled$":[{"__symbolic":"property","decorators":[{"__symbolic":"call","expression":{"__symbolic":"reference","module":"@ngrx/effects","name":"Effect","line":99,"character":2}}]}],"DoSignout$":[{"__symbolic":"property","decorators":[{"__symbolic":"call","expression":{"__symbolic":"reference","module":"@ngrx/effects","name":"Effect","line":101,"character":2}}]}],"redirectToLoginPage$":[{"__symbolic":"property","decorators":[{"__symbolic":"call","expression":{"__symbolic":"reference","module":"@ngrx/effects","name":"Effect","line":118,"character":2},"arguments":[{"dispatch":false}]}]}],"redirectAfterSignout$":[{"__symbolic":"property","decorators":[{"__symbolic":"call","expression":{"__symbolic":"reference","module":"@ngrx/effects","name":"Effect","line":123,"character":2},"arguments":[{"dispatch":false}]}]}]}},"ɵq":{"__symbolic":"class","decorators":[{"__symbolic":"call","expression":{"__symbolic":"reference","module":"@angular/core","name":"Injectable","line":12,"character":1}}],"members":{"__ctor__":[{"__symbolic":"constructor","parameters":[{"__symbolic":"reference","name":"Actions","module":"@ngrx/effects","arguments":[{"__symbolic":"reference","name":"any"}]},{"__symbolic":"reference","module":"@angular/router","name":"Router","line":14,"character":61}]}],"dispachProgressingStarted$":[{"__symbolic":"property","decorators":[{"__symbolic":"call","expression":{"__symbolic":"reference","module":"@ngrx/effects","name":"Effect","line":16,"character":2}}]}],"dispachProgressingFinished$":[{"__symbolic":"property","decorators":[{"__symbolic":"call","expression":{"__symbolic":"reference","module":"@ngrx/effects","name":"Effect","line":21,"character":2}}]}]}},"ɵr":{"__symbolic":"call","expression":{"__symbolic":"select","expression":{"__symbolic":"reference","module":"@angular/router","name":"RouterModule","line":27,"character":64},"member":"forChild"},"arguments":[[{"path":"auth","component":{"__symbolic":"reference","name":"ɵj"},"children":[{"path":"signin","component":{"__symbolic":"reference","name":"SigninContainerComponent"}},{"path":"signup","component":{"__symbolic":"reference","name":"ɵk"}}]}]]},"ɵs":{"__symbolic":"class","decorators":[{"__symbolic":"call","expression":{"__symbolic":"reference","module":"@angular/core","name":"Injectable","line":15,"character":1}}],"members":{"__ctor__":[{"__symbolic":"constructor","parameters":[{"__symbolic":"reference","module":"@angular/router","name":"Router","line":18,"character":18},{"__symbolic":"reference","name":"Store","module":"@ngrx/store","arguments":[{"__symbolic":"reference","name":"ɵe"}]}]}],"intercept":[{"__symbolic":"method"}]}},"ɵt":{"__symbolic":"class","decorators":[{"__symbolic":"call","expression":{"__symbolic":"reference","module":"@angular/core","name":"Injectable","line":11,"character":1}}],"members":{"__ctor__":[{"__symbolic":"constructor","parameters":[{"__symbolic":"reference","name":"ɵf"}]}],"intercept":[{"__symbolic":"method"}]}}},"origins":{"SigninService":"./lib/services/signin.service","SigninContainerComponent":"./lib/smart-components/signin-container/signin-container.component","ɵa":"./lib/authentication.module","NgsAuthenticationModule":"./lib/authentication.module","ɵb":"./lib/reducers/index","ɵc":"./lib/reducers/index","ɵd":"./lib/reducers/index","getUser":"./lib/reducers/index","ɵe":"./lib/reducers","ɵf":"./lib/services/authentication-configuration.service","ɵg":"./lib/authentication.config","ɵh":"./lib/reducers","ɵi":"./lib/dump-components/signin/signin.component","ɵj":"./lib/smart-components/authentication-container/authentication-container.component","ɵk":"./lib/smart-components/signup-container/signup-container.component","ɵl":"./lib/dump-components/signup/signup.component","ɵm":"./lib/routing-guards/signin.guard","ɵn":"./lib/reducers/user.reducer","ɵo":"./lib/reducers/user.reducer","ɵp":"./lib/effects/signin.effects","ɵq":"./lib/effects/authentication.effects","ɵr":"./lib/authentication-routing.module","ɵs":"./lib/interceptors/unauthorized.interceptor","ɵt":"./lib/interceptors/with-credential.interceptor"},"importAs":"@soushians/authentication"}