{"__symbolic":"module","version":4,"exports":[{"export":[{"name":"GwtStep","as":"GwtStep"},{"name":"GwtStepTypes","as":"GwtStepTypes"},{"name":"GwtGivenStepUi","as":"GwtGivenStepUi"},{"name":"GwtThenStepUi","as":"GwtThenStepUi"}],"from":"./lib/models"},{"export":[{"name":"ShowAnchorsAction","as":"ShowAnchorsAction"},{"name":"HideAnchorsAction","as":"HideAnchorsAction"}],"from":"./lib/rule-anchor"}],"metadata":{"RuleModule":{"__symbolic":"class","decorators":[{"__symbolic":"call","expression":{"__symbolic":"reference","module":"@angular/core","name":"NgModule","line":39,"character":1},"arguments":[{"imports":[{"__symbolic":"reference","module":"@angular/common/http","name":"HttpClientModule","line":41,"character":2},{"__symbolic":"reference","module":"@angular/forms","name":"FormsModule","line":42,"character":2},{"__symbolic":"reference","module":"@angular/router","name":"RouterModule","line":43,"character":2},{"__symbolic":"reference","module":"@angular/common","name":"CommonModule","line":44,"character":2},{"__symbolic":"reference","module":"@angular/material","name":"MatExpansionModule","line":45,"character":2},{"__symbolic":"reference","module":"@angular/material","name":"MatSnackBarModule","line":46,"character":2},{"__symbolic":"reference","module":"@angular/material","name":"MatIconModule","line":47,"character":2},{"__symbolic":"reference","module":"@angular/material","name":"MatButtonModule","line":48,"character":2},{"__symbolic":"reference","module":"@angular/material","name":"MatCardModule","line":49,"character":2},{"__symbolic":"reference","module":"@angular/material","name":"MatCheckboxModule","line":50,"character":2},{"__symbolic":"reference","module":"@angular/material","name":"MatTableModule","line":51,"character":2},{"__symbolic":"reference","module":"@angular/material","name":"MatSelectModule","line":52,"character":2},{"__symbolic":"reference","module":"@angular/material","name":"MatInputModule","line":53,"character":2},{"__symbolic":"reference","module":"@angular/material","name":"MatFormFieldModule","line":54,"character":2},{"__symbolic":"reference","module":"@angular/material","name":"MatTabsModule","line":55,"character":2},{"__symbolic":"reference","module":"@angular/material","name":"MatDividerModule","line":56,"character":2},{"__symbolic":"reference","module":"@angular/flex-layout","name":"FlexLayoutModule","line":57,"character":2},{"__symbolic":"reference","module":"@angular/material","name":"MatRadioModule","line":58,"character":2},{"__symbolic":"reference","module":"@angular/material","name":"MatSlideToggleModule","line":59,"character":2},{"__symbolic":"reference","module":"@angular/forms","name":"ReactiveFormsModule","line":60,"character":2},{"__symbolic":"reference","module":"@angular/platform-browser/animations","name":"BrowserAnimationsModule","line":61,"character":2}],"declarations":[{"__symbolic":"reference","name":"ɵa"},{"__symbolic":"reference","name":"ɵb"},{"__symbolic":"reference","name":"ɵi"},{"__symbolic":"reference","name":"ɵj"},{"__symbolic":"reference","name":"ɵk"}],"entryComponents":[{"__symbolic":"reference","name":"ɵi"}],"exports":[{"__symbolic":"reference","name":"ɵb"},{"__symbolic":"reference","name":"ɵk"}]}]}],"members":{},"statics":{"forRoot":{"__symbolic":"function","parameters":["config"],"value":{"ngModule":{"__symbolic":"reference","name":"RootRuleModule"},"providers":[{"provide":{"__symbolic":"reference","name":"MODULE_CONFIG_TOKEN"},"useValue":{"__symbolic":"binop","operator":"||","left":{"__symbolic":"reference","name":"config"},"right":{}}},{"__symbolic":"reference","name":"ɵr"},{"__symbolic":"reference","name":"ɵh"}]}}}},"RootRuleModule":{"__symbolic":"class","decorators":[{"__symbolic":"call","expression":{"__symbolic":"reference","module":"@angular/core","name":"NgModule","line":80,"character":1},"arguments":[{"imports":[{"__symbolic":"reference","name":"RuleModule"},{"__symbolic":"call","expression":{"__symbolic":"select","expression":{"__symbolic":"reference","module":"@ngrx/store","name":"StoreModule","line":83,"character":2},"member":"forFeature"},"arguments":["rule",{"__symbolic":"reference","name":"ɵe"}]},{"__symbolic":"call","expression":{"__symbolic":"select","expression":{"__symbolic":"reference","module":"@ngrx/effects","name":"EffectsModule","line":84,"character":2},"member":"forFeature"},"arguments":[[{"__symbolic":"reference","name":"ɵo"},{"__symbolic":"reference","name":"ɵp"}]]},{"__symbolic":"reference","name":"ɵq"}],"exports":[{"__symbolic":"reference","name":"RuleModule"}]}]}],"members":{}},"RuleModuleConfig":{"__symbolic":"interface"},"MODULE_DEFAULT_CONFIG":{"endpoints":{"upsert":"/api/gwt/scenario","get":"/api/gwt/anchor/${model.anchorId}/scenarios"},"stepClasses":[],"env":{"production":false,"frontend_server":"http://localhost:3000"}},"MODULE_CONFIG_TOKEN":{"__symbolic":"new","expression":{"__symbolic":"reference","module":"@angular/core","name":"InjectionToken","line":26,"character":39},"arguments":["RuleModuleConfig"]},"ɵa":{"__symbolic":"class","decorators":[{"__symbolic":"call","expression":{"__symbolic":"reference","module":"@angular/core","name":"Component","line":2,"character":1},"arguments":[{"selector":"app-rule","template":"<div fxLayout=\"row\" fxLayoutAlign=\"center center\">\n  <router-outlet></router-outlet>\n</div>"}]}],"members":{"__ctor__":[{"__symbolic":"constructor"}],"ngOnInit":[{"__symbolic":"method"}]}},"ɵb":{"__symbolic":"class","decorators":[{"__symbolic":"call","expression":{"__symbolic":"reference","module":"@angular/core","name":"Directive","line":14,"character":1},"arguments":[{"selector":"[ruleAnchor]"}]}],"members":{"anchorId":[{"__symbolic":"property","decorators":[{"__symbolic":"call","expression":{"__symbolic":"reference","module":"@angular/core","name":"Input","line":19,"character":2},"arguments":["ruleAnchor"]}]}],"__ctor__":[{"__symbolic":"constructor","parameters":[{"__symbolic":"reference","name":"ɵc"},{"__symbolic":"reference","name":"ɵh"},{"__symbolic":"reference","name":"Store","module":"@ngrx/store","arguments":[{"__symbolic":"reference","name":"ɵf"}]},{"__symbolic":"reference","module":"@angular/core","name":"ElementRef","line":29,"character":14},{"__symbolic":"reference","module":"@angular/core","name":"Renderer2","line":30,"character":20},{"__symbolic":"reference","module":"@angular/material","name":"MatBottomSheet","line":31,"character":23}]}],"onMouseEnter":[{"__symbolic":"method","decorators":[{"__symbolic":"call","expression":{"__symbolic":"reference","module":"@angular/core","name":"HostListener","line":39,"character":2},"arguments":["mouseenter"]}]}],"onMouseLeave":[{"__symbolic":"method","decorators":[{"__symbolic":"call","expression":{"__symbolic":"reference","module":"@angular/core","name":"HostListener","line":45,"character":2},"arguments":["mouseleave"]}]}],"showAnchor":[{"__symbolic":"method"}],"hideAnchor":[{"__symbolic":"method"}],"ngOnInit":[{"__symbolic":"method"}],"ngOnDestroy":[{"__symbolic":"method"}],"_activate_anchor":[{"__symbolic":"method"}],"_deactivate_anchor":[{"__symbolic":"method"}],"_set_active_class_to_host":[{"__symbolic":"method"}],"_remove_active_class_to_host":[{"__symbolic":"method"}],"_create_anchor":[{"__symbolic":"method"}],"_remove_anchor":[{"__symbolic":"method"}],"_do_scenario":[{"__symbolic":"method"}]}},"ɵc":{"__symbolic":"class","decorators":[{"__symbolic":"call","expression":{"__symbolic":"reference","module":"@angular/core","name":"Injectable","line":14,"character":1},"arguments":[{"providedIn":"root"}]}],"members":{"__ctor__":[{"__symbolic":"constructor","parameters":[{"__symbolic":"reference","module":"@angular/common/http","name":"HttpClient","line":21,"character":16},{"__symbolic":"reference","name":"Store","module":"@ngrx/store","arguments":[{"__symbolic":"reference","name":"ɵf"}]},{"__symbolic":"reference","name":"ɵg"}]}],"upsert":[{"__symbolic":"method"}],"getAnchorScenarios":[{"__symbolic":"method"}],"selectScenarioById":[{"__symbolic":"method"}],"selectAnchorScenarios":[{"__symbolic":"method"}]},"statics":{"ngInjectableDef":{}}},"ɵd":{"__symbolic":"interface"},"ɵe":{"ruleAnchors":{"__symbolic":"reference","name":"ɵl"},"rules":{"__symbolic":"reference","name":"ɵm"},"scenarios":{"__symbolic":"reference","name":"ɵn"}},"ɵf":{"__symbolic":"interface"},"ɵg":{"__symbolic":"class","decorators":[{"__symbolic":"call","expression":{"__symbolic":"reference","module":"@angular/core","name":"Injectable","line":10,"character":1}}],"members":{"__ctor__":[{"__symbolic":"constructor","parameterDecorators":[[{"__symbolic":"call","expression":{"__symbolic":"reference","module":"@angular/core","name":"Inject","line":19,"character":3},"arguments":[{"__symbolic":"reference","name":"MODULE_CONFIG_TOKEN"}]}],null,null],"parameters":[{"__symbolic":"reference","name":"RuleModuleConfig"},{"__symbolic":"reference","name":"Store","module":"@ngrx/store","arguments":[{"__symbolic":"reference","name":"ɵd"}]},{"__symbolic":"reference","module":"@angular/core","name":"Injector","line":21,"character":20}]}]}},"ɵi":{"__symbolic":"class","decorators":[{"__symbolic":"call","expression":{"__symbolic":"reference","module":"@angular/core","name":"Component","line":16,"character":1},"arguments":[{"selector":"app-gwt-view","template":"<div fxLayout=\"row\" fxLayoutGap=\"25px\">\n<div fxFlex=\"400px\" fxLayout=\"column\" fxLayoutGap=\"15px\">\n  <div fxLayout=\"row wrap\">\n    <mat-form-field appearance=\"fill\" fxFlex=\"100\">\n      <input matInput placeholder=\"فیلتر\">\n      <mat-icon matSuffix>search</mat-icon>\n    </mat-form-field>\n    <mat-checkbox fxFlex class=\"example-margin\">فرض کنید</mat-checkbox>\n    <mat-checkbox fxFlex class=\"example-margin\">هنگامی که</mat-checkbox>\n    <mat-checkbox fxFlex class=\"example-margin\">آنگاه</mat-checkbox>\n  </div>\n    <mat-card class=\"steps-item\" *ngFor=\"let step of steps$ | async\">\n      <span class=\"step-text\">\n        {{step.description}}\n      </span>\n      <button mat-icon-button class=\"add-button\" (click)=\"addStepToScenario(step)\">\n        <mat-icon>arrow_back_ios</mat-icon>\n      </button>\n    </mat-card>\n</div>\n\n<div fxFlex=\"700px\">\n  <div fxLayout=\"row wrap\" fxLayoutGap=\"25px\" fxLayoutAlign=\"center center\" class=\"scenario-toolbar\">\n    <div fxFlex>\n        <mat-form-field class=\"fit\">\n            <mat-select placeholder=\"وِیژگی\" (selectionChange)=\"activeScenario($event.value)\">\n                  <mat-option *ngFor=\"let scenario of scenarios$ | async\" [value]=\"scenario\">\n                {{ scenario.featureId }} : {{ scenario.name }}\n              </mat-option>\n            </mat-select>\n          </mat-form-field>\n    </div>\n    <button fxFlex=\"nogrow\" mat-raised-button color=\"primary\" (click)=\"addNewScenario()\">\n       ثبت سناریو جدید\n    </button>\n  </div>\n  <div fxLayout=\"column\" fxLayoutGap=\"15px\">\n    <div fxFlex=\"100\" fxLayout=\"row\" fxLayoutGap=\"25px\" [formGroup]=\"scenarioFormGroup\">\n      <mat-form-field fxFlex=\"50\">\n        <mat-select placeholder=\"ویژگی\" formControlName=\"featureId\">\n          <mat-option *ngFor=\"let feature of features$\" [value]=\"feature\">\n            {{ feature }}\n          </mat-option>\n        </mat-select>\n      </mat-form-field>\n      <mat-form-field fxFlex=\"50\">\n        <input matInput placeholder=\"نام\" formControlName=\"name\">\n      </mat-form-field>\n    </div>\n    <ng-container *ngFor=\"let step of (scenario$ | async).steps\">\n      <div class=\"scenario-steps-item\">\n        <ng-container rule-step-loader [step]=\"step\"></ng-container>\n        <div class=\"scenario-steps-action\">\n          <button mat-icon-button (click)=\"deleteStepFromScenario(step)\">\n            <mat-icon>delete</mat-icon>\n          </button>\n          <button mat-icon-button (click)=\"incScenarioStepPriority(step)\">\n            <mat-icon>keyboard_arrow_up</mat-icon>\n          </button>\n          <button mat-icon-button (click)=\"decScenarioStepPriority(step)\">\n            <mat-icon>keyboard_arrow_down</mat-icon>\n          </button>\n        </div>\n      </div>\n    </ng-container>\n      <button fxFlex=\"nogrow\" mat-raised-button color=\"primary\" (click)=\"save()\">\n        ثبت\n      </button>\n    </div>\n  </div>\n</div>","styles":[":host{width:100vw}.scenario-toolbar{height:60px;margin-bottom:20px}"]}]}],"members":{"stepLoaders":[{"__symbolic":"property","decorators":[{"__symbolic":"call","expression":{"__symbolic":"reference","module":"@angular/core","name":"ViewChildren","line":99,"character":2},"arguments":[{"__symbolic":"reference","name":"ɵj"}]}]}],"__ctor__":[{"__symbolic":"constructor","parameterDecorators":[null,null,null,null,[{"__symbolic":"call","expression":{"__symbolic":"reference","module":"@angular/core","name":"Inject","line":105,"character":3},"arguments":[{"__symbolic":"reference","module":"@angular/material","name":"MAT_BOTTOM_SHEET_DATA","line":105,"character":10}]}]],"parameters":[{"__symbolic":"reference","name":"Store","module":"@ngrx/store","arguments":[{"__symbolic":"reference","name":"ɵf"}]},{"__symbolic":"reference","name":"ɵh"},{"__symbolic":"reference","name":"ɵc"},{"__symbolic":"reference","module":"@angular/core","name":"Injector","line":104,"character":20},{"__symbolic":"reference","name":"any"}]}],"ngOnInit":[{"__symbolic":"method"}],"ngOnDestroy":[{"__symbolic":"method"}],"save":[{"__symbolic":"method"}],"addStepToScenario":[{"__symbolic":"method"}],"deleteStepFromScenario":[{"__symbolic":"method"}],"decScenarioStepPriority":[{"__symbolic":"method"}],"incScenarioStepPriority":[{"__symbolic":"method"}],"addNewScenario":[{"__symbolic":"method"}],"activeScenario":[{"__symbolic":"method"}],"_load_scenario_and_map_scenario_step_to_steps_class":[{"__symbolic":"method"}],"_create_scenario_form_group":[{"__symbolic":"method"}],"_reset_scenario_form_group_and_patch_with_active_scenario":[{"__symbolic":"method"}],"_init_features_list":[{"__symbolic":"method"}]}},"ɵj":{"__symbolic":"class","decorators":[{"__symbolic":"call","expression":{"__symbolic":"reference","module":"@angular/core","name":"Directive","line":14,"character":1},"arguments":[{"selector":"[rule-step-loader]"}]}],"members":{"step":[{"__symbolic":"property","decorators":[{"__symbolic":"call","expression":{"__symbolic":"reference","module":"@angular/core","name":"Input","line":20,"character":2}}]}],"component":[{"__symbolic":"property","decorators":[{"__symbolic":"call","expression":{"__symbolic":"reference","module":"@angular/core","name":"ViewChild","line":21,"character":2},"arguments":["container",{"read":{"__symbolic":"reference","module":"@angular/core","name":"ViewContainerRef","line":21,"character":33}}]}]}],"__ctor__":[{"__symbolic":"constructor","parameters":[{"__symbolic":"reference","module":"@angular/core","name":"ComponentFactoryResolver","line":27,"character":31},{"__symbolic":"reference","module":"@angular/core","name":"ViewContainerRef","line":27,"character":76}]}],"ngOnChanges":[{"__symbolic":"method"}],"ngOnInit":[{"__symbolic":"method"}]}},"ɵk":{"__symbolic":"class","decorators":[{"__symbolic":"call","expression":{"__symbolic":"reference","module":"@angular/core","name":"Component","line":8,"character":1},"arguments":[{"selector":"gwt-mode-button","template":"    <button *ngIf=\"!(havePermission$ | async)\" class=\"btn\" mat-mini-fab type=\"button\" routerLink=\"auth/frontend/signin\" fxFlex=\"nogrow\" fxLayoutAlign=\"center center\">\n      <mat-icon>fingerprint</mat-icon>\n    </button>\n\n    <button *ngIf=\"havePermission$ | async\" class=\"btn\" mat-mini-fab type=\"button\" (click)=\"toggleAnchors()\" fxFlex=\"nogrow\" fxLayoutAlign=\"center center\">\n      <mat-icon>settings</mat-icon>\n    </button>","styles":[".btn{position:fixed;bottom:25px;right:25px;z-index:3}"]}]}],"members":{"__ctor__":[{"__symbolic":"constructor","parameters":[{"__symbolic":"reference","name":"Store","module":"@ngrx/store","arguments":[{"__symbolic":"reference","name":"any"}]}]}],"toggleAnchors":[{"__symbolic":"method"}]}},"ɵm":{"__symbolic":"function"},"ɵn":{"__symbolic":"function"},"ɵo":{"__symbolic":"class","decorators":[{"__symbolic":"call","expression":{"__symbolic":"reference","module":"@angular/core","name":"Injectable","line":6,"character":1}}],"members":{"__ctor__":[{"__symbolic":"constructor","parameters":[{"__symbolic":"reference","name":"Actions","module":"@ngrx/effects","arguments":[{"__symbolic":"reference","name":"any"}]}]}],"EditProfileRequest$":[{"__symbolic":"property","decorators":[{"__symbolic":"call","expression":{"__symbolic":"reference","module":"@ngrx/effects","name":"Effect","line":10,"character":2}}]}]}},"ɵp":{"__symbolic":"class","decorators":[{"__symbolic":"call","expression":{"__symbolic":"reference","module":"@angular/core","name":"Injectable","line":8,"character":1}}],"members":{"__ctor__":[{"__symbolic":"constructor","parameters":[{"__symbolic":"reference","name":"Actions","module":"@ngrx/effects","arguments":[{"__symbolic":"reference","name":"any"}]},{"__symbolic":"reference","name":"ɵc"}]}],"EditProfileRequest$":[{"__symbolic":"property","decorators":[{"__symbolic":"call","expression":{"__symbolic":"reference","module":"@ngrx/effects","name":"Effect","line":12,"character":2}}]}],"UpsertScenario$":[{"__symbolic":"property","decorators":[{"__symbolic":"call","expression":{"__symbolic":"reference","module":"@ngrx/effects","name":"Effect","line":17,"character":2}}]}]}},"ɵq":{"__symbolic":"call","expression":{"__symbolic":"select","expression":{"__symbolic":"reference","module":"@angular/router","name":"RouterModule","line":13,"character":50},"member":"forChild"},"arguments":[[{"path":"rule","component":{"__symbolic":"reference","name":"ɵa"}}]]}},"origins":{"RuleModule":"./lib/rule.module","RootRuleModule":"./lib/rule.module","RuleModuleConfig":"./lib/rule.config","MODULE_DEFAULT_CONFIG":"./lib/rule.config","MODULE_CONFIG_TOKEN":"./lib/rule.config","ɵa":"./lib/rule.component","ɵb":"./lib/rule-anchor/rule-anchor.directive","ɵc":"./lib/services/scenario.service","ɵd":"./lib/rule.reducers","ɵe":"./lib/rule.reducers","ɵf":"./lib/rule.reducers","ɵg":"./lib/services/rule-configuration.service","ɵh":"./lib/services","ɵi":"./lib/gwt-view/gwt-view.component","ɵj":"./lib/step-loader/step-loader.directive","ɵk":"./lib/mode-button/mode-button.component","ɵl":"./lib/rule-anchor","ɵm":"./lib/db/rule-db.reducer","ɵn":"./lib/db/scenario-db.reducer","ɵo":"./lib/db/rule-db.effects","ɵp":"./lib/db/scenario-db.effects","ɵq":"./lib/rule-routing.module","ɵr":"./lib/services"},"importAs":"@soushians/rule"}